LICENSE
README.md
setup.py
dz_mongodb/__init__.py
dz_mongodb/config_utils.py
dz_mongodb/datetime_utils.py
dz_mongodb/db_utils.py
dz_mongodb/errors.py
dz_mongodb/stream_utils.py
dz_mongodb.egg-info/PKG-INFO
dz_mongodb.egg-info/SOURCES.txt
dz_mongodb.egg-info/dependency_links.txt
dz_mongodb.egg-info/entry_points.txt
dz_mongodb.egg-info/requires.txt
dz_mongodb.egg-info/top_level.txt
dz_mongodb/sync_strategies/change_streams.py
dz_mongodb/sync_strategies/common.py
dz_mongodb/sync_strategies/full_table.py
dz_mongodb/sync_strategies/incremental.py