Metadata-Version: 2.1
Name: dz-mongodb
Version: 1.4.5
Summary: Singer.io tap for extracting data from MongoDB - Datazip compatible
Home-page: https://github.com/datazip/dz-mongodb
Author: Wise
License: UNKNOWN
Platform: UNKNOWN
Classifier: Programming Language :: Python :: 3 :: Only
Classifier: Programming Language :: Python :: 3.6
Classifier: Programming Language :: Python :: 3.7
Classifier: Programming Language :: Python :: 3.8
Provides-Extra: dev
Provides-Extra: test
License-File: LICENSE
